{"artists":[{"idArtist":"175929","strArtist":"\u5433\u9752\u5cf0","strArtistStripped":null,"strArtistAlternate":null,"strLabel":null,"idLabel":null,"intFormedYear":"1982","intBornYear":null,"intDiedYear":null,"strDisbanded":null,"strStyle":null,"strGenre":"","strMood":null,"strWebsite":null,"strFacebook":null,"strTwitter":null,"strBiographyEN":"","strBiographyDE":null,"strBiographyFR":null,"strBiographyCN":null,"strBiographyIT":null,"strBiographyJP":null,"strBiographyRU":null,"strBiographyES":null,"strBiographyPT":null,"strBiographySE":null,"strBiographyNL":null,"strBiographyHU":null,"strBiographyNO":null,"strBiographyIL":null,"strBiographyPL":null,"strGender":null,"intMembers":null,"strCountry":null,"strCountryCode":"TW","strArtistThumb":null,"strArtistLogo":null,"strArtistCutout":null,"strArtistClearart":null,"strArtistWideThumb":null,"strArtistFanart":null,"strArtistFanart2":null,"strArtistFanart3":null,"strArtistFanart4":null,"strArtistBanner":null,"strMusicBrainzID":"6109bc84-838a-462f-8dd6-0aa42914501b","strISNIcode":null,"strLastFMChart":null,"intCharted":"0","strLocked":"unlocked"}]}