{"artists":[{"idArtist":"152521","strArtist":"Karol G","strArtistStripped":null,"strArtistAlternate":"Carolina Giraldo Navarro","strLabel":null,"idLabel":null,"intFormedYear":"1991","intBornYear":"1991","intDiedYear":null,"strDisbanded":null,"strStyle":"","strGenre":"Latin","strMood":"","strWebsite":"","strFacebook":"","strTwitter":"1","strBiographyEN":"Carolina Giraldo Navarro, known professionally as Karol G, is a Colombian reggaeton singer and songwriter. Her songs \"Ahora Me Llama\", \"Mi Cama\" and \"Culpables\" have reached the top ten on the Billboard Hot Latin Songs chart. She has won a Latin Grammy Award.","strBiographyDE":null,"strBiographyFR":null,"strBiographyCN":null,"strBiographyIT":null,"strBiographyJP":null,"strBiographyRU":null,"strBiographyES":null,"strBiographyPT":null,"strBiographySE":null,"strBiographyNL":null,"strBiographyHU":null,"strBiographyNO":null,"strBiographyIL":null,"strBiographyPL":null,"strGender":"Female","intMembers":"1","strCountry":"","strCountryCode":"CO","strArtistThumb":"https://www.theaudiodb.com/images/media/artist/thumb/uxvwty1543482498.jpg","strArtistLogo":"https://www.theaudiodb.com/images/media/artist/logo/tqyusw1543491957.png","strArtistCutout":"https://www.theaudiodb.com/images/media/artist/cutout/29dbba1677323239.png","strArtistClearart":"https://www.theaudiodb.com/images/media/artist/clearart/wvqpwt1547660106.png","strArtistWideThumb":"https://www.theaudiodb.com/images/media/artist/widethumb/rvxyqt1547660089.jpg","strArtistFanart":"https://www.theaudiodb.com/images/media/artist/fanart/vtwrxs1547660263.jpg","strArtistFanart2":"https://www.theaudiodb.com/images/media/artist/fanart/uuutvu1547660324.jpg","strArtistFanart3":"https://www.theaudiodb.com/images/media/artist/fanart/xsvsux1547660438.jpg","strArtistFanart4":"https://www.theaudiodb.com/images/media/artist/fanart/5b78a71677577614.jpg","strArtistBanner":"https://www.theaudiodb.com/images/media/artist/banner/vyryxw1547660202.jpg","strMusicBrainzID":"de22adae-f8ac-414f-b653-b0162611bd60","strISNIcode":null,"strLastFMChart":null,"intCharted":"4","strLocked":"unlocked"}]}